GermaniumLibrary
