Metadata-Version: 1.0
Name: robotframework-germaniumlibrary
Version: 1.0.1
Summary: GermaniumLibrary
Home-page: UNKNOWN
Author: Bogdan Mustiata
Author-email: bogdan.mustiata@gmail.com
License: BSD
Platform: UNKNOWN
